jfx_bridge/__init__.py
jfx_bridge/bridge.py
jfx_bridge/test_bridge.py
jfx_bridge/test_module.py
jfx_bridge-1.0.0.dist-info/LICENSE
jfx_bridge-1.0.0.dist-info/METADATA
jfx_bridge-1.0.0.dist-info/WHEEL
jfx_bridge-1.0.0.dist-info/top_level.txt
jfx_bridge-1.0.0.dist-info/RECORD
