Metadata-Version: 2.1
Name: jfx_bridge
Version: 1.0.0
Summary: RPC bridge to/from Python2/Python3/Jython/etc
Home-page: https://github.com/justfoxing/jfx_bridge
Author: justfoxing
Author-email: justfoxingprojects@gmail.com
Classifier: Programming Language :: Python
Classifier: License :: OSI Approved :: MIT License
Classifier: Operating System :: OS Independent
License-File: LICENSE
